drift_scope/__init__.py
drift_scope/_sql.py
drift_scope/_utils.py
drift_scope/base.py
drift_scope/dataframe.py
drift_scope/results.py
drift_scope/sql.py
drift_scope-0.1.0.dist-info/METADATA
drift_scope-0.1.0.dist-info/WHEEL
drift_scope-0.1.0.dist-info/RECORD
