Metadata-Version: 2.4
Name: drift-scope
Version: 0.1.0
Summary: Add your description here
Author-email: Tyler Riccio <tylerriccio8@gmail.com>
Requires-Python: >=3.12
Requires-Dist: narwhals>=1.27.1
Requires-Dist: pyarrow>=19.0.1
Requires-Dist: rich>=13.9.4
